poelis_sdk/__init__.py
poelis_sdk/_transport.py
poelis_sdk/browser.py
poelis_sdk/change_tracker.py
poelis_sdk/client.py
poelis_sdk/exceptions.py
poelis_sdk/items.py
poelis_sdk/logging.py
poelis_sdk/matlab_facade.py
poelis_sdk/models.py
poelis_sdk/org_validation.py
poelis_sdk/products.py
poelis_sdk/properties.py
poelis_sdk/search.py
poelis_sdk/versions.py
poelis_sdk/workspaces.py
poelis_sdk/_browser/__init__.py
poelis_sdk/_browser/_graphql_errors.py
poelis_sdk/_browser/completion.py
poelis_sdk/_browser/nodes.py
poelis_sdk/_browser/props.py
poelis_sdk/_browser/public.py
poelis_sdk/_browser/utils.py
poelis_sdk/_browser/node/__init__.py
poelis_sdk/_browser/node/cache.py
poelis_sdk/_browser/node/children.py
poelis_sdk/_browser/node/core.py
poelis_sdk/_browser/node/lists.py
poelis_sdk/_browser/node/properties.py
poelis_sdk/_browser/node/versions.py
poelis_sdk-1.0.3.dist-info/METADATA
poelis_sdk-1.0.3.dist-info/WHEEL
poelis_sdk-1.0.3.dist-info/licenses/LICENSE
poelis_sdk-1.0.3.dist-info/RECORD
