Metadata-Version: 2.4
Name: poelis-sdk
Version: 1.0.3
Summary: Official Python SDK for Poelis
Project-URL: Homepage, https://poelis.com
Project-URL: Source, https://github.com/PoelisTechnologies/poelis-python-sdk
Project-URL: Issues, https://github.com/PoelisTechnologies/poelis-python-sdk/issues
Author-email: Matteo Braceschi <matteo@poelis.com>
License-Expression: MIT
License-File: LICENSE
Keywords: api,client,poelis,sdk
Classifier: Intended Audience :: Developers
Classifier: License :: OSI Approved :: MIT License
Classifier: Programming Language :: Python :: 3
Classifier: Programming Language :: Python :: 3.11
Classifier: Topic :: Software Development :: Libraries
Requires-Python: >=3.11
Requires-Dist: build>=1.3.0
Requires-Dist: httpx>=0.27
Requires-Dist: pydantic>=2.7
Requires-Dist: twine>=6.2.0
